_util_cluster.py
_util_kcluster.py
kcluster.py
kcluster-0.0.2.dist-info/LICENSE.txt
kcluster-0.0.2.dist-info/METADATA
kcluster-0.0.2.dist-info/WHEEL
kcluster-0.0.2.dist-info/top_level.txt
kcluster-0.0.2.dist-info/RECORD
